{
  "parent": "minecraft:adventure/root",
  "display": {
    "icon": {
      "id": "swordssmp:thunder_sword"
    },
    "title": {
      "text": "Thunder Sword"
    },
    "description": {
      "text": "Hold Thunder Sword in your inventory"
    },
    "frame": "task",
    "show_toast": true,
    "announce_to_chat": true,
    "hidden": false
  },
  "criteria": {
    "has_thunder_blade": {
      "trigger": "minecraft:inventory_changed",
      "conditions": {
        "items": [
          {
            "items": [
              "swordssmp:thunder_sword"
            ]
          }
        ]
      }
    }
  },
  "requirements": [
    [
      "has_thunder_blade"
    ]
  ]
}
